LICENSE
MANIFEST.in
README.md
setup.py
bufrpy/__init__.py
bufrpy/bufrdec.py
bufrpy/compat.py
bufrpy/descriptors.py
bufrpy/json.py
bufrpy/util.py
bufrpy/value.py
bufrpy.egg-info/PKG-INFO
bufrpy.egg-info/SOURCES.txt
bufrpy.egg-info/dependency_links.txt
bufrpy.egg-info/not-zip-safe
bufrpy.egg-info/requires.txt
bufrpy.egg-info/top_level.txt
bufrpy/table/__init__.py
bufrpy/table/libbufr.py
bufrpy/template/__init__.py
bufrpy/template/safnwc.py
bufrpy/tool/__init__.py
bufrpy/tool/bufr2json.py