Metadata-Version: 1.1
Name: bufrpy
Version: 0.2.2
Summary: Pyre-Python BUFR decoder
Home-page: https://github.com/tazle/bufrpy
Author: Tuure Laurinolli
Author-email: tuure@laurinolli.net
License: UNKNOWN
Keywords: bufr
Platform: UNKNOWN
Classifier: Programming Language :: Python
Classifier: Programming Language :: Python :: 3
Classifier: Intended Audience :: Developers
Classifier: License :: OSI Approved :: GNU General Public License v2 or later (GPLv2+)
Classifier: Topic :: Scientific/Engineering
